{"type":"FeatureCollection","features":[{"type":"Feature","id":1,"geometry":{"type":"Point","coordinates":[5.2253087006833612,52.401880153800342]},"properties":{"OBJECTID":1,"FID_campings":2056,"fid_1":2057,"name":"Waterhout - Almere (05/04-27/10)  (-4m) +31365470632","afstand":750,"FID_gemeente_2021_v1":1,"GM_CODE":"GM0034","GM_NAAM":"Almere","H2O":"NEE","OAD":1616,"STED":2,"BEV_DICHTH":1662,"AANT_INW":214715,"AANT_MAN":106523,"AANT_VROUW":108192,"P_00_14_JR":18,"P_15_24_JR":13,"P_25_44_JR":28,"P_45_64_JR":28,"P_65_EO_JR":12,"P_ONGEHUWD":53,"P_GEHUWD":36,"P_GESCHEID":9,"P_VERWEDUW":3,"AANTAL_HH":90426,"P_EENP_HH":32,"P_HH_Z_K":25,"P_HH_M_K":43,"GEM_HH_GR":2.2999999999999998,"P_WEST_AL":11,"P_N_W_AL":34,"P_MAROKKO":4,"P_ANT_ARU":0,"P_SURINAM":12,"P_TURKIJE":2,"P_OVER_NW":16,"OPP_TOT":24877,"OPP_LAND":12919,"OPP_WATER":11958,"JRSTATCODE":"2021GM0034","JAAR":2021,"Shape_Leng":77001.560698200003}},{"type":"Feature","id":2,"geometry":{"type":"Point","coordinates":[5.3024696247531793,52.319830345942613]},"properties":{"OBJECTID":2,"FID_campings":1943,"fid_1":1944,"name":"Naturist - Hamaland - Almere (01/04-30/09)  (0m) +31651722257","afstand":3000,"FID_gemeente_2021_v1":1,"GM_CODE":"GM0034","GM_NAAM":"Almere","H2O":"NEE","OAD":1616,"STED":2,"BEV_DICHTH":1662,"AANT_INW":214715,"AANT_MAN":106523,"AANT_VROUW":108192,"P_00_14_JR":18,"P_15_24_JR":13,"P_25_44_JR":28,"P_45_64_JR":28,"P_65_EO_JR":12,"P_ONGEHUWD":53,"P_GEHUWD":36,"P_GESCHEID":9,"P_VERWEDUW":3,"AANTAL_HH":90426,"P_EENP_HH":32,"P_HH_Z_K":25,"P_HH_M_K":43,"GEM_HH_GR":2.2999999999999998,"P_WEST_AL":11,"P_N_W_AL":34,"P_MAROKKO":4,"P_ANT_ARU":0,"P_SURINAM":12,"P_TURKIJE":2,"P_OVER_NW":16,"OPP_TOT":24877,"OPP_LAND":12919,"OPP_WATER":11958,"JRSTATCODE":"2021GM0034","JAAR":2021,"Shape_Leng":77001.560698200003}},{"type":"Feature","id":3,"geometry":{"type":"Point","coordinates":[5.2698993189090357,52.343030165800343]},"properties":{"OBJECTID":3,"FID_campings":1975,"fid_1":1976,"name":"Natuur De Kemphaan - Almere [\u003c51] (01/01-31/12)  (-2m) +31653704075","afstand":1000,"FID_gemeente_2021_v1":1,"GM_CODE":"GM0034","GM_NAAM":"Almere","H2O":"NEE","OAD":1616,"STED":2,"BEV_DICHTH":1662,"AANT_INW":214715,"AANT_MAN":106523,"AANT_VROUW":108192,"P_00_14_JR":18,"P_15_24_JR":13,"P_25_44_JR":28,"P_45_64_JR":28,"P_65_EO_JR":12,"P_ONGEHUWD":53,"P_GEHUWD":36,"P_GESCHEID":9,"P_VERWEDUW":3,"AANTAL_HH":90426,"P_EENP_HH":32,"P_HH_Z_K":25,"P_HH_M_K":43,"GEM_HH_GR":2.2999999999999998,"P_WEST_AL":11,"P_N_W_AL":34,"P_MAROKKO":4,"P_ANT_ARU":0,"P_SURINAM":12,"P_TURKIJE":2,"P_OVER_NW":16,"OPP_TOT":24877,"OPP_LAND":12919,"OPP_WATER":11958,"JRSTATCODE":"2021GM0034","JAAR":2021,"Shape_Leng":77001.560698200003}}]}